MAOC/__init__.py
MAOC/maoc.py
maoc-0.0.1.dist-info/METADATA
maoc-0.0.1.dist-info/WHEEL
maoc-0.0.1.dist-info/licenses/LICENSE
maoc-0.0.1.dist-info/RECORD
