Metadata-Version: 2.1
Name: MAOC
Version: 0.0.1
Summary: The script required to create the recently proposed MAOC representation 
Author-email: Stiv Llenga <stiv.llenga@h-its.org>, "Ganna (Anya) Gryn'ova" <ganna.grynova@h-its.org>
License-File: LICENSE
Classifier: License :: OSI Approved :: MIT License
Classifier: Operating System :: OS Independent
Classifier: Programming Language :: Python :: 3
Requires-Python: >=3.7
